<annotation>
	<folder></folder>
	<filename>anders_l5_jpg.rf.e511922d950f534cc864ab34ec7640b5.jpg</filename>
	<path>anders_l5_jpg.rf.e511922d950f534cc864ab34ec7640b5.jpg</path>
	<source>
		<database>roboflow.com</database>
	</source>
	<size>
		<width>400</width>
		<height>300</height>
		<depth>3</depth>
	</size>
	<segmented>0</segmented>
	<object>
		<name>tanks</name>
		<pose>Unspecified</pose>
		<truncated>0</truncated>
		<difficult>0</difficult>
		<occluded>0</occluded>
		<bndbox>
			<xmin>197</xmin>
			<xmax>401</xmax>
			<ymin>1</ymin>
			<ymax>145</ymax>
		</bndbox>
		<polygon>
			<x1>400</x1>
			<y1>144</y1>
			<x2>400</x2>
			<y2>0.059734</y2>
			<x3>332.140423</x3>
			<y3>2.429443</y3>
			<x4>252.933822</x4>
			<y4>30.558766</y4>
			<x5>261.147852</x5>
			<y5>33.44005</y5>
			<x6>262.581925</x6>
			<y6>41.044169</y6>
			<x7>213.268622</x7>
			<y7>62.982725</y7>
			<x8>206.553571</x8>
			<y8>63.15475</y8>
			<x9>205.888977</x9>
			<y9>58.227692</y9>
			<x10>196</x10>
			<y10>62.255869</y10>
			<x11>196</x11>
			<y11>66.715558</y11>
			<x12>199.139127</x12>
			<y12>68.738237</y12>
			<x13>196</x13>
			<y13>70.169821</y13>
			<x14>196</x14>
			<y14>73.76264</y14>
			<x15>216.188618</x15>
			<y15>144</y15>
			<x16>400</x16>
			<y16>144</y16>
		</polygon>
	</object>
	<object>
		<name>tanks</name>
		<pose>Unspecified</pose>
		<truncated>0</truncated>
		<difficult>0</difficult>
		<occluded>0</occluded>
		<bndbox>
			<xmin>193</xmin>
			<xmax>287</xmax>
			<ymin>1</ymin>
			<ymax>86</ymax>
		</bndbox>
		<polygon>
			<x1>192</x1>
			<y1>0</y1>
			<x2>192</x2>
			<y2>85.310851</y2>
			<x3>214.765625</x3>
			<y3>81.769531</y3>
			<x4>218.867188</x4>
			<y4>43.488281</y4>
			<x5>214.765625</x5>
			<y5>21.613281</y5>
			<x6>222.285156</x6>
			<y6>8.625</y6>
			<x7>233.222656</x7>
			<y7>9.992188</y7>
			<x8>240.058594</x8>
			<y8>15.460938</y8>
			<x9>282.44140600000003</x9>
			<y9>12.726562</y9>
			<x10>285.859375</x10>
			<y10>9.308594</y10>
			<x11>283.997656</x11>
			<y11>0</y11>
			<x12>192</x12>
			<y12>0</y12>
		</polygon>
	</object>
	<object>
		<name>tanks</name>
		<pose>Unspecified</pose>
		<truncated>0</truncated>
		<difficult>0</difficult>
		<occluded>0</occluded>
		<bndbox>
			<xmin>1</xmin>
			<xmax>193</xmax>
			<ymin>145</ymin>
			<ymax>301</ymax>
		</bndbox>
		<polygon>
			<x1>192</x1>
			<y1>144</y1>
			<x2>0</x2>
			<y2>144</y2>
			<x3>0</x3>
			<y3>300</y3>
			<x4>62.536027</x4>
			<y4>300</y4>
			<x5>71.95399</x5>
			<y5>296.65531799999997</y5>
			<x6>69.368109</x6>
			<y6>294.025419</y6>
			<x7>77.605652</x7>
			<y7>262.66792599999997</y7>
			<x8>81.301608</x8>
			<y8>260.51939600000003</y8>
			<x9>96.055691</x9>
			<y9>272.840011</y9>
			<x10>97.800453</x10>
			<y10>278.91013899999996</y10>
			<x11>106.807085</x11>
			<y11>283.23832100000004</y11>
			<x12>111.618046</x12>
			<y12>282.56908</y12>
			<x13>156.090303</x13>
			<y13>266.775262</y13>
			<x14>170.266692</x14>
			<y14>233.942318</y14>
			<x15>179.529124</x15>
			<y15>233.160728</y15>
			<x16>178.836714</x16>
			<y16>236.751508</y16>
			<x17>188.407438</x17>
			<y17>240.042338</y17>
			<x18>185.456824</x18>
			<y18>247.779977</y18>
			<x19>192</x19>
			<y19>250.24327399999999</y19>
			<x20>192</x20>
			<y20>144</y20>
		</polygon>
	</object>
	<object>
		<name>tanks</name>
		<pose>Unspecified</pose>
		<truncated>0</truncated>
		<difficult>0</difficult>
		<occluded>0</occluded>
		<bndbox>
			<xmin>309</xmin>
			<xmax>400</xmax>
			<ymin>145</ymin>
			<ymax>215</ymax>
		</bndbox>
		<polygon>
			<x1>314.802036</x1>
			<y1>192.35869</y1>
			<x2>321.657849</x2>
			<y2>203.368788</y2>
			<x3>362.873578</x3>
			<y3>213.58273400000002</y3>
			<x4>376.056554</x4>
			<y4>213.58273400000002</y4>
			<x5>398.579093</x5>
			<y5>200.635322</y5>
			<x6>399.307513</x6>
			<y6>171.698189</y6>
			<x7>394.47607300000004</x7>
			<y7>144.489608</y7>
			<x8>352.531727</x8>
			<y8>146.860571</y8>
			<x9>308.48</x9>
			<y9>172.184353</y9>
			<x10>308.48</x10>
			<y10>179.373608</y10>
			<x11>313.775171</x11>
			<y11>181.557852</y11>
			<x12>314.802036</x12>
			<y12>192.35869</y12>
		</polygon>
	</object>
</annotation>
