<annotation>
	<folder></folder>
	<filename>challenger_2_l1_jpg.rf.713de83698495efd49499dd85dff3980.jpg</filename>
	<path>challenger_2_l1_jpg.rf.713de83698495efd49499dd85dff3980.jpg</path>
	<source>
		<database>roboflow.com</database>
	</source>
	<size>
		<width>512</width>
		<height>409</height>
		<depth>3</depth>
	</size>
	<segmented>0</segmented>
	<object>
		<name>tanks</name>
		<pose>Unspecified</pose>
		<truncated>0</truncated>
		<difficult>0</difficult>
		<occluded>0</occluded>
		<bndbox>
			<xmin>1</xmin>
			<xmax>297</xmax>
			<ymin>121</ymin>
			<ymax>410</ymax>
		</bndbox>
		<polygon>
			<x1>296</x1>
			<y1>409</y1>
			<x2>288</x2>
			<y2>401</y2>
			<x3>284</x3>
			<y3>373</y3>
			<x4>267</x4>
			<y4>364</y4>
			<x5>251</x5>
			<y5>362</y5>
			<x6>236</x6>
			<y6>349</y6>
			<x7>230</x7>
			<y7>273</y7>
			<x8>222</x8>
			<y8>251</y8>
			<x9>207</x9>
			<y9>242</y9>
			<x10>152</x10>
			<y10>229</y10>
			<x11>148</x11>
			<y11>213</y11>
			<x12>150</x12>
			<y12>205</y12>
			<x13>158</x13>
			<y13>199</y13>
			<x14>160</x14>
			<y14>189</y14>
			<x15>160</x15>
			<y15>169</y15>
			<x16>157</x16>
			<y16>166</y16>
			<x17>152</x17>
			<y17>169</y17>
			<x18>152</x18>
			<y18>179</y18>
			<x19>139</x19>
			<y19>194</y19>
			<x20>129</x20>
			<y20>182</y20>
			<x21>126</x21>
			<y21>183</y21>
			<x22>127</x22>
			<y22>192</y22>
			<x23>109</x23>
			<y23>192</y23>
			<x24>110</x24>
			<y24>181</y24>
			<x25>125</x25>
			<y25>178</y25>
			<x26>126</x26>
			<y26>173</y26>
			<x27>102</x27>
			<y27>161</y27>
			<x28>102</x28>
			<y28>153</y28>
			<x29>96</x29>
			<y29>149</y29>
			<x30>102</x30>
			<y30>143</y30>
			<x31>98</x31>
			<y31>127</y31>
			<x32>91</x32>
			<y32>120</y32>
			<x33>73</x33>
			<y33>120</y33>
			<x34>66</x34>
			<y34>127</y34>
			<x35>64</x35>
			<y35>143</y35>
			<x36>86</x36>
			<y36>145</y36>
			<x37>64</x37>
			<y37>155</y37>
			<x38>71</x38>
			<y38>158</y38>
			<x39>70</x39>
			<y39>163</y39>
			<x40>74</x40>
			<y40>165</y40>
			<x41>56</x41>
			<y41>181</y41>
			<x42>49</x42>
			<y42>196</y42>
			<x43>42</x43>
			<y43>197</y43>
			<x44>44</x44>
			<y44>189</y44>
			<x45>41</x45>
			<y45>186</y45>
			<x46>30</x46>
			<y46>189</y46>
			<x47>28</x47>
			<y47>199</y47>
			<x48>40</x48>
			<y48>205</y48>
			<x49>34</x49>
			<y49>209</y49>
			<x50>34</x50>
			<y50>225</y50>
			<x51>21</x51>
			<y51>232</y51>
			<x52>0</x52>
			<y52>232</y52>
			<x53>0</x53>
			<y53>409</y53>
			<x54>296</x54>
			<y54>409</y54>
		</polygon>
	</object>
</annotation>
