<annotation>
	<folder></folder>
	<filename>k21_105_l4_jpg.rf.0531f5fa77cab489c43c482bc3fbf1bb.jpg</filename>
	<path>k21_105_l4_jpg.rf.0531f5fa77cab489c43c482bc3fbf1bb.jpg</path>
	<source>
		<database>roboflow.com</database>
	</source>
	<size>
		<width>512</width>
		<height>384</height>
		<depth>3</depth>
	</size>
	<segmented>0</segmented>
	<object>
		<name>tanks</name>
		<pose>Unspecified</pose>
		<truncated>0</truncated>
		<difficult>0</difficult>
		<occluded>0</occluded>
		<bndbox>
			<xmin>335</xmin>
			<xmax>394</xmax>
			<ymin>108</ymin>
			<ymax>154</ymax>
		</bndbox>
		<polygon>
			<x1>392.538787</x1>
			<y1>153</y1>
			<x2>392.551176</x2>
			<y2>152.836501</y2>
			<x3>392.21596</x3>
			<y3>141.505003</y3>
			<x4>385.687179</x4>
			<y4>142.23755</y4>
			<x5>380.508688</x5>
			<y5>106.727185</y5>
			<x6>338.508322</x6>
			<y6>114.508091</y6>
			<x7>337.469865</x7>
			<y7>148.960273</y7>
			<x8>334.217541</x8>
			<y8>153</y8>
			<x9>392.538787</x9>
			<y9>153</y9>
		</polygon>
	</object>
	<object>
		<name>tanks</name>
		<pose>Unspecified</pose>
		<truncated>0</truncated>
		<difficult>0</difficult>
		<occluded>0</occluded>
		<bndbox>
			<xmin>1</xmin>
			<xmax>241</xmax>
			<ymin>225</ymin>
			<ymax>306</ymax>
		</bndbox>
		<polygon>
			<x1>240</x1>
			<y1>261.421641</y1>
			<x2>173.169276</x2>
			<y2>247.956402</y2>
			<x3>130.897983</x3>
			<y3>245.369472</y3>
			<x4>20.624806</x4>
			<y4>226.20996300000002</y4>
			<x5>0</x5>
			<y5>224.31754999999998</y5>
			<x6>0</x6>
			<y6>281.983257</y6>
			<x7>240</x7>
			<y7>304.575823</y7>
			<x8>240</x8>
			<y8>261.421641</y8>
		</polygon>
	</object>
	<object>
		<name>tanks</name>
		<pose>Unspecified</pose>
		<truncated>0</truncated>
		<difficult>0</difficult>
		<occluded>0</occluded>
		<bndbox>
			<xmin>241</xmin>
			<xmax>444</xmax>
			<ymin>260</ymin>
			<ymax>385</ymax>
		</bndbox>
		<polygon>
			<x1>442.998878</x1>
			<y1>384</y1>
			<x2>428.559806</x2>
			<y2>374.786431</y2>
			<x3>419.447951</x3>
			<y3>353.495404</y3>
			<x4>388.03852</x4>
			<y4>331.112665</y4>
			<x5>375.200467</x5>
			<y5>327.223998</y5>
			<x6>354.111016</x6>
			<y6>331.130989</y6>
			<x7>341.211501</x7>
			<y7>325.16470300000003</y7>
			<x8>240</x8>
			<y8>258.757925</y8>
			<x9>240</x9>
			<y9>307.164982</y9>
			<x10>314.532753</x10>
			<y10>355.175234</y10>
			<x11>333.16559</x11>
			<y11>375.74692600000003</y11>
			<x12>344.43039899999997</x12>
			<y12>384</y12>
			<x13>442.998878</x13>
			<y13>384</y13>
		</polygon>
	</object>
</annotation>
