<annotation>
	<folder></folder>
	<filename>m1a2_abrams_l4_jpg.rf.142e10a27e46a7dcd45e9027af0adf18.jpg</filename>
	<path>m1a2_abrams_l4_jpg.rf.142e10a27e46a7dcd45e9027af0adf18.jpg</path>
	<source>
		<database>roboflow.com</database>
	</source>
	<size>
		<width>512</width>
		<height>345</height>
		<depth>3</depth>
	</size>
	<segmented>0</segmented>
	<object>
		<name>tanks</name>
		<pose>Unspecified</pose>
		<truncated>0</truncated>
		<difficult>0</difficult>
		<occluded>0</occluded>
		<bndbox>
			<xmin>40</xmin>
			<xmax>161</xmax>
			<ymin>87</ymin>
			<ymax>197</ymax>
		</bndbox>
		<polygon>
			<x1>160.263503</x1>
			<y1>196</y1>
			<x2>159.422054</x2>
			<y2>179.737969</y2>
			<x3>154.292446</x3>
			<y3>173.72411</y3>
			<x4>122.662935</x4>
			<y4>175.618322</y4>
			<x5>103.351904</x5>
			<y5>150.542413</y5>
			<x6>103.114875</x6>
			<y6>125.904474</y6>
			<x7>96.959346</x7>
			<y7>118.687842</y7>
			<x8>111.448183</x8>
			<y8>106.442233</y8>
			<x9>109.759301</x9>
			<y9>99.590211</y9>
			<x10>119.237045</x10>
			<y10>93.64971</y10>
			<x11>117.185204</x11>
			<y11>91.244166</y11>
			<x12>47.952133</x12>
			<y12>85.59272</y12>
			<x13>38.939666</x13>
			<y13>196</y13>
			<x14>160.263503</x14>
			<y14>196</y14>
		</polygon>
	</object>
	<object>
		<name>tanks</name>
		<pose>Unspecified</pose>
		<truncated>0</truncated>
		<difficult>0</difficult>
		<occluded>0</occluded>
		<bndbox>
			<xmin>387</xmin>
			<xmax>402</xmax>
			<ymin>190</ymin>
			<ymax>197</ymax>
		</bndbox>
		<polygon>
			<x1>400.666667</x1>
			<y1>196</y1>
			<x2>400.666667</x2>
			<y2>194.469901</y2>
			<x3>386.616844</x3>
			<y3>188.830899</y3>
			<x4>386.365274</x4>
			<y4>194.129538</y4>
			<x5>386.355296</x5>
			<y5>195.60394</y5>
			<x6>389.17733699999997</x6>
			<y6>196</y6>
			<x7>400.666667</x7>
			<y7>196</y7>
		</polygon>
	</object>
	<object>
		<name>tanks</name>
		<pose>Unspecified</pose>
		<truncated>0</truncated>
		<difficult>0</difficult>
		<occluded>0</occluded>
		<bndbox>
			<xmin>357</xmin>
			<xmax>384</xmax>
			<ymin>27</ymin>
			<ymax>197</ymax>
		</bndbox>
		<polygon>
			<x1>382.910503</x1>
			<y1>196</y1>
			<x2>378.26579200000003</x2>
			<y2>174.924279</y2>
			<x3>369.368223</x3>
			<y3>173.420172</y3>
			<x4>368.923343</x4>
			<y4>151.610634</y4>
			<x5>372.482371</x5>
			<y5>151.610634</y5>
			<x6>374.706764</x6>
			<y6>158.37911</y6>
			<x7>369.368223</x7>
			<y7>164.395535</y7>
			<x8>373.372129</x8>
			<y8>171.164014</y8>
			<x9>376.041399</x9>
			<y9>165.147588</y9>
			<x10>377.376035</x10>
			<y10>170.411959</y10>
			<x11>375.596521</x11>
			<y11>144.842157</y11>
			<x12>380.935063</x12>
			<y12>128.296988</y12>
			<x13>376.48627799999997</x13>
			<y13>89.190229</y13>
			<x14>369.368223</x14>
			<y14>81.6697</y14>
			<x15>367.14383</x15>
			<y15>71.893009</y15>
			<x16>366.254073</x16>
			<y16>77.909433</y16>
			<x17>362.695046</x17>
			<y17>77.909433</y17>
			<x18>361.36041</x18>
			<y18>69.63685</y18>
			<x19>364.029681</x19>
			<y19>68.132743</y19>
			<x20>358.691139</x20>
			<y20>63.620425</y20>
			<x21>360.47065299999997</x21>
			<y21>42.562939</y21>
			<x22>357.801382</x22>
			<y22>39.554728</y22>
			<x23>361.36041</x23>
			<y23>32.034195</y23>
			<x24>358.691139</x24>
			<y24>29.025983</y24>
			<x25>358.691139</x25>
			<y25>25.789474</y25>
			<x26>356.333333</x26>
			<y26>25.789474</y26>
			<x27>356.333333</x27>
			<y27>42.111876</y27>
			<x28>357.801382</x28>
			<y28>47.075257</y28>
			<x29>357.801382</x29>
			<y29>75.653274</y29>
			<x30>356.333333</x30>
			<y30>80.971182</y30>
			<x31>356.333333</x31>
			<y31>196</y31>
			<x32>382.910503</x32>
			<y32>196</y32>
		</polygon>
	</object>
	<object>
		<name>tanks</name>
		<pose>Unspecified</pose>
		<truncated>0</truncated>
		<difficult>0</difficult>
		<occluded>0</occluded>
		<bndbox>
			<xmin>1</xmin>
			<xmax>200</xmax>
			<ymin>197</ymin>
			<ymax>346</ymax>
		</bndbox>
		<polygon>
			<x1>0</x1>
			<y1>196</y1>
			<x2>0</x2>
			<y2>345</y2>
			<x3>153.277227</x3>
			<y3>345</y3>
			<x4>157.782489</x4>
			<y4>312.301716</y4>
			<x5>161.398457</x5>
			<y5>309.230045</y5>
			<x6>167.902355</x6>
			<y6>312.005514</y6>
			<x7>174.110977</x7>
			<y7>304.656362</y7>
			<x8>183.846509</x8>
			<y8>240.358847</y8>
			<x9>191.260453</x9>
			<y9>231.985806</y9>
			<x10>190.30588</x10>
			<y10>216.195972</y10>
			<x11>197.674322</x11>
			<y11>208.380355</y11>
			<x12>198.684921</x12>
			<y12>196</y12>
			<x13>0</x13>
			<y13>196</y13>
		</polygon>
	</object>
</annotation>
