<annotation>
	<folder></folder>
	<filename>m84_l1_jpg.rf.463193a94270882c16b1cf7836da221b.jpg</filename>
	<path>m84_l1_jpg.rf.463193a94270882c16b1cf7836da221b.jpg</path>
	<source>
		<database>roboflow.com</database>
	</source>
	<size>
		<width>512</width>
		<height>384</height>
		<depth>3</depth>
	</size>
	<segmented>0</segmented>
	<object>
		<name>tanks</name>
		<pose>Unspecified</pose>
		<truncated>0</truncated>
		<difficult>0</difficult>
		<occluded>0</occluded>
		<bndbox>
			<xmin>100</xmin>
			<xmax>195</xmax>
			<ymin>36</ymin>
			<ymax>212</ymax>
		</bndbox>
		<polygon>
			<x1>194</x1>
			<y1>88.513767</y1>
			<x2>186.053106</x2>
			<y2>95.461303</y2>
			<x3>178.769884</x3>
			<y3>94.552376</y3>
			<x4>183.242478</x4>
			<y4>80.16443</y4>
			<x5>181.570583</x5>
			<y5>72.021426</y5>
			<x6>173.717994</x6>
			<y6>67.535565</y6>
			<x7>179.112085</x7>
			<y7>44.774702</y7>
			<x8>176.85071</x8>
			<y8>36.415973</y8>
			<x9>170.657396</x9>
			<y9>34.912042</y9>
			<x10>152.53753</x10>
			<y10>35.731801</y10>
			<x11>99</x11>
			<y11>207.957381</y11>
			<x12>99</x12>
			<y12>211</y12>
			<x13>135.099705</x13>
			<y13>211</y13>
			<x14>138.651432</x14>
			<y14>196.56726</y14>
			<x15>149.982706</x15>
			<y15>189.862495</y15>
			<x16>155.241902</x16>
			<y16>194.578267</y16>
			<x17>168.24507</x17>
			<y17>196.016507</y17>
			<x18>178.510021</x18>
			<y18>187.33347</y18>
			<x19>182.946409</x19>
			<y19>170.357726</y19>
			<x20>194</x20>
			<y20>173.62969</y20>
			<x21>194</x21>
			<y21>155.055415</y21>
			<x22>179.530209</x22>
			<y22>148.896122</y22>
			<x23>176.828199</x23>
			<y23>141.362641</y23>
			<x24>173.20469</x24>
			<y24>142.202077</y24>
			<x25>167.909287</x25>
			<y25>134.898507</y25>
			<x26>179.52028</x26>
			<y26>111.068298</y26>
			<x27>193.58977</x27>
			<y27>114.484811</y27>
			<x28>194</x28>
			<y28>115.628574</y28>
			<x29>194</x29>
			<y29>88.513767</y29>
		</polygon>
	</object>
	<object>
		<name>tanks</name>
		<pose>Unspecified</pose>
		<truncated>0</truncated>
		<difficult>0</difficult>
		<occluded>0</occluded>
		<bndbox>
			<xmin>1</xmin>
			<xmax>36</xmax>
			<ymin>201</ymin>
			<ymax>216</ymax>
		</bndbox>
		<polygon>
			<x1>0</x1>
			<y1>215</y1>
			<x2>31.191289</x2>
			<y2>215</y2>
			<x3>33.119147</x3>
			<y3>212.730054</y3>
			<x4>35.201733</x4>
			<y4>205.358511</y4>
			<x5>25.004257</x5>
			<y5>200.979909</y5>
			<x6>0</x6>
			<y6>199.686807</y6>
			<x7>0</x7>
			<y7>215</y7>
		</polygon>
	</object>
	<object>
		<name>tanks</name>
		<pose>Unspecified</pose>
		<truncated>0</truncated>
		<difficult>0</difficult>
		<occluded>0</occluded>
		<bndbox>
			<xmin>195</xmin>
			<xmax>471</xmax>
			<ymin>1</ymin>
			<ymax>216</ymax>
		</bndbox>
		<polygon>
			<x1>215.5488</x1>
			<y1>0</y1>
			<x2>194</x2>
			<y2>69.320617</y2>
			<x3>194</x3>
			<y3>203.952104</y3>
			<x4>239.496163</x4>
			<y4>215</y4>
			<x5>309.344551</x5>
			<y5>215</y5>
			<x6>310.870403</x6>
			<y6>209.739674</y6>
			<x7>318.193569</x7>
			<y7>205.372484</y7>
			<x8>322.634595</x8>
			<y8>191.086091</y8>
			<x9>334.145349</x9>
			<y9>190.040611</y9>
			<x10>350.39694</x10>
			<y10>200.132492</y10>
			<x11>362.324679</x11>
			<y11>195.347617</y11>
			<x12>369.367801</x12>
			<y12>206.276134</y12>
			<x13>380.017659</x13>
			<y13>210.398075</y13>
			<x14>406.256841</x14>
			<y14>207.551544</y14>
			<x15>422.00935400000003</x15>
			<y15>214.449491</y15>
			<x16>429.776432</x16>
			<y16>208.654277</y16>
			<x17>445.030863</x17>
			<y17>212.358531</y17>
			<x18>447.750452</x18>
			<y18>208.409268</y18>
			<x19>461.906987</x19>
			<y19>214.608344</y19>
			<x20>470.065549</x20>
			<y20>188.362959</y20>
			<x21>470.065549</x21>
			<y21>182.484236</y21>
			<x22>467.226877</x22>
			<y22>179.33749</y22>
			<x23>452.027294</x23>
			<y23>180.256217</y23>
			<x24>449.199999</x24>
			<y24>174.959998</y24>
			<x25>443.68004099999996</x25>
			<y25>175.924411</y25>
			<x26>451.78233</x26>
			<y26>159.455447</y26>
			<x27>414.429616</x27>
			<y27>118.888602</y27>
			<x28>397.78896199999997</x28>
			<y28>114.847729</y28>
			<x29>390.990803</x29>
			<y29>124.719981</y29>
			<x30>384.52885100000003</x30>
			<y30>123.918727</y30>
			<x31>382.171399</x31>
			<y31>119.505611</y31>
			<x32>386.722119</x32>
			<y32>114.465184</y32>
			<x33>382.09062</x33>
			<y33>112.571499</y33>
			<x34>382.479685</x34>
			<y34>106.520492</y34>
			<x35>369.998697</x35>
			<y35>103.489717</y35>
			<x36>352.13469</x36>
			<y36>112.979665</y36>
			<x37>338.02152</x37>
			<y37>88.811259</y37>
			<x38>344.846605</x38>
			<y38>81.250378</y38>
			<x39>339.689104</x39>
			<y39>73.851388</y39>
			<x40>348.489738</x40>
			<y40>38.34654</y40>
			<x41>312.877904</x41>
			<y41>28.163049</y41>
			<x42>302.617428</x42>
			<y42>17.989077</y42>
			<x43>284.145326</x43>
			<y43>15.040392</y43>
			<x44>286.338912</x44>
			<y44>5.585826</y44>
			<x45>301.607544</x45>
			<y45>0</y45>
			<x46>215.5488</x46>
			<y46>0</y46>
		</polygon>
	</object>
	<object>
		<name>tanks</name>
		<pose>Unspecified</pose>
		<truncated>0</truncated>
		<difficult>0</difficult>
		<occluded>0</occluded>
		<bndbox>
			<xmin>1</xmin>
			<xmax>180</xmax>
			<ymin>216</ymin>
			<ymax>385</ymax>
		</bndbox>
		<polygon>
			<x1>0</x1>
			<y1>215</y1>
			<x2>0</x2>
			<y2>384</y2>
			<x3>168.112178</x3>
			<y3>384</y3>
			<x4>178.775228</x4>
			<y4>349.697896</y4>
			<x5>178.775228</x5>
			<y5>344.928802</y5>
			<x6>170.70375</x6>
			<y6>337.683593</y6>
			<x7>170.433439</x7>
			<y7>317.837043</y7>
			<x8>164.400628</x8>
			<y8>313.075269</y8>
			<x9>133.741003</x9>
			<y9>252.881058</y9>
			<x10>123.761405</x10>
			<y10>250.457699</y10>
			<x11>110.605446</x11>
			<y11>258.252414</y11>
			<x12>102.621767</x12>
			<y12>256.313726</y12>
			<x13>90.466041</x13>
			<y13>240.17466100000001</y13>
			<x14>78.490523</x14>
			<y14>237.26663</y14>
			<x15>63.338645</x15>
			<y15>244.576672</y15>
			<x16>47.371287</x16>
			<y16>240.699296</y16>
			<x17>43.334396</x17>
			<y17>236.422195</y17>
			<x18>49.77722</x18>
			<y18>222.601562</y18>
			<x19>43.549779</x19>
			<y19>215</y19>
			<x20>0</x20>
			<y20>215</y20>
		</polygon>
	</object>
</annotation>
