<annotation>
	<folder></folder>
	<filename>m8_buford_l1_jpg.rf.b3d28021d86e5b343d8c95bf59354c01.jpg</filename>
	<path>m8_buford_l1_jpg.rf.b3d28021d86e5b343d8c95bf59354c01.jpg</path>
	<source>
		<database>roboflow.com</database>
	</source>
	<size>
		<width>512</width>
		<height>384</height>
		<depth>3</depth>
	</size>
	<segmented>0</segmented>
	<object>
		<name>tanks</name>
		<pose>Unspecified</pose>
		<truncated>0</truncated>
		<difficult>0</difficult>
		<occluded>0</occluded>
		<bndbox>
			<xmin>1</xmin>
			<xmax>214</xmax>
			<ymin>1</ymin>
			<ymax>196</ymax>
		</bndbox>
		<polygon>
			<x1>16.247141</x1>
			<y1>0</y1>
			<x2>0</x2>
			<y2>3.6823</y2>
			<x3>0</x3>
			<y3>103.613319</y3>
			<x4>0.236366</x4>
			<y4>104.408593</y4>
			<x5>0</x5>
			<y5>104.60297</y5>
			<x6>0</x6>
			<y6>195</y6>
			<x7>172.938254</x7>
			<y7>195</y7>
			<x8>171.437974</x8>
			<y8>179.730923</y8>
			<x9>204.50276</x9>
			<y9>171.410037</y9>
			<x10>209.823532</x10>
			<y10>167.723167</y10>
			<x11>212.787825</x11>
			<y11>160.002143</y11>
			<x12>208.641519</x12>
			<y12>131.039588</y12>
			<x13>186.070126</x13>
			<y13>118.52568</y13>
			<x14>193.474649</x14>
			<y14>111.885587</y14>
			<x15>199.044431</x15>
			<y15>92.429558</y15>
			<x16>203.065969</x16>
			<y16>92.093549</y16>
			<x17>189.881774</x17>
			<y17>0</y17>
			<x18>16.247141</x18>
			<y18>0</y18>
		</polygon>
	</object>
	<object>
		<name>tanks</name>
		<pose>Unspecified</pose>
		<truncated>0</truncated>
		<difficult>0</difficult>
		<occluded>0</occluded>
		<bndbox>
			<xmin>147</xmin>
			<xmax>246</xmax>
			<ymin>196</ymin>
			<ymax>385</ymax>
		</bndbox>
		<polygon>
			<x1>245</x1>
			<y1>384</y1>
			<x2>245</x2>
			<y2>195.034491</y2>
			<x3>146.289987</x3>
			<y3>217.406419</y3>
			<x4>146</x4>
			<y4>219.366753</y4>
			<x5>146</x5>
			<y5>330.973699</y5>
			<x6>153.591293</x6>
			<y6>384</y6>
			<x7>245</x7>
			<y7>384</y7>
		</polygon>
	</object>
	<object>
		<name>tanks</name>
		<pose>Unspecified</pose>
		<truncated>0</truncated>
		<difficult>0</difficult>
		<occluded>0</occluded>
		<bndbox>
			<xmin>312</xmin>
			<xmax>418</xmax>
			<ymin>196</ymin>
			<ymax>270</ymax>
		</bndbox>
		<polygon>
			<x1>311.307602</x1>
			<y1>195</y1>
			<x2>316.682809</x2>
			<y2>232.546613</y2>
			<x3>341.928126</x3>
			<y3>255.176324</y3>
			<x4>368.598997</x4>
			<y4>269.204015</y4>
			<x5>400.635651</x5>
			<y5>268.28180299999997</y5>
			<x6>414.603139</x6>
			<y6>253.495275</y6>
			<x7>416.743235</x7>
			<y7>195</y7>
			<x8>311.307602</x8>
			<y8>195</y8>
		</polygon>
	</object>
</annotation>
