<annotation>
	<folder></folder>
	<filename>mars_15_main_jpg.rf.a9d63dc0fefbf99ae852d53fb44ef938.jpg</filename>
	<path>mars_15_main_jpg.rf.a9d63dc0fefbf99ae852d53fb44ef938.jpg</path>
	<source>
		<database>roboflow.com</database>
	</source>
	<size>
		<width>512</width>
		<height>353</height>
		<depth>3</depth>
	</size>
	<segmented>0</segmented>
	<object>
		<name>tanks</name>
		<pose>Unspecified</pose>
		<truncated>0</truncated>
		<difficult>0</difficult>
		<occluded>0</occluded>
		<bndbox>
			<xmin>89</xmin>
			<xmax>306</xmax>
			<ymin>1</ymin>
			<ymax>183</ymax>
		</bndbox>
		<polygon>
			<x1>102.954535</x1>
			<y1>120.440332</y1>
			<x2>116.585921</x2>
			<y2>161.584365</y2>
			<x3>120.626884</x3>
			<y3>170.662438</y3>
			<x4>128.126839</x4>
			<y4>178.053172</y4>
			<x5>191.093608</x5>
			<y5>182.4</y5>
			<x6>205.363989</x6>
			<y6>182.4</y6>
			<x7>304.587478</x7>
			<y7>165.188082</y7>
			<x8>304.587478</x8>
			<y8>163.799815</y8>
			<x9>293.55642</x9>
			<y9>130.504433</y9>
			<x10>287.739621</x10>
			<y10>124.509953</y10>
			<x11>290.157534</x11>
			<y11>120.24547</y11>
			<x12>250.396956</x12>
			<y12>0.234897</y12>
			<x13>116.056696</x13>
			<y13>0.234897</y13>
			<x14>87.62</x14>
			<y14>5.167701</y14>
			<x15>87.62</x15>
			<y15>12.421113</y15>
			<x16>97.618477</x16>
			<y16>49.601011</y16>
			<x17>102.954535</x17>
			<y17>120.440332</y17>
		</polygon>
	</object>
	<object>
		<name>tanks</name>
		<pose>Unspecified</pose>
		<truncated>0</truncated>
		<difficult>0</difficult>
		<occluded>0</occluded>
		<bndbox>
			<xmin>117</xmin>
			<xmax>338</xmax>
			<ymin>191</ymin>
			<ymax>339</ymax>
		</bndbox>
		<polygon>
			<x1>337</x1>
			<y1>190</y1>
			<x2>116.028446</x2>
			<y2>190</y2>
			<x3>130.931298</x3>
			<y3>243.18893500000001</y3>
			<x4>158.497874</x4>
			<y4>316.54554</y4>
			<x5>168.234617</x5>
			<y5>324.452715</y5>
			<x6>215.2617</x6>
			<y6>338</y6>
			<x7>220.221368</x7>
			<y7>338</y7>
			<x8>239.67796</x8>
			<y8>334.009139</y8>
			<x9>251.458564</x9>
			<y9>335.47452599999997</y9>
			<x10>337</x10>
			<y10>317.9286</y10>
			<x11>337</x11>
			<y11>190</y11>
		</polygon>
	</object>
	<object>
		<name>tanks</name>
		<pose>Unspecified</pose>
		<truncated>0</truncated>
		<difficult>0</difficult>
		<occluded>0</occluded>
		<bndbox>
			<xmin>1</xmin>
			<xmax>138</xmax>
			<ymin>191</ymin>
			<ymax>297</ymax>
		</bndbox>
		<polygon>
			<x1>0</x1>
			<y1>190</y1>
			<x2>0</x2>
			<y2>264.833333</y2>
			<x3>5</x3>
			<y3>279</y3>
			<x4>16</x4>
			<y4>290</y4>
			<x5>84</x5>
			<y5>296</y5>
			<x6>137</x6>
			<y6>295</y6>
			<x7>131</x7>
			<y7>273</y7>
			<x8>131</x8>
			<y8>253</y8>
			<x9>117</x9>
			<y9>235</y9>
			<x10>117</x10>
			<y10>205</y10>
			<x11>123</x11>
			<y11>195</y11>
			<x12>123</x12>
			<y12>190</y12>
			<x13>0</x13>
			<y13>190</y13>
		</polygon>
	</object>
	<object>
		<name>tanks</name>
		<pose>Unspecified</pose>
		<truncated>0</truncated>
		<difficult>0</difficult>
		<occluded>0</occluded>
		<bndbox>
			<xmin>338</xmin>
			<xmax>470</xmax>
			<ymin>191</ymin>
			<ymax>354</ymax>
		</bndbox>
		<polygon>
			<x1>337</x1>
			<y1>190</y1>
			<x2>337</x2>
			<y2>300.412263</y2>
			<x3>349.105539</x3>
			<y3>314.992231</y3>
			<x4>353.88732600000003</x4>
			<y4>314.011409</y4>
			<x5>352.524119</x5>
			<y5>309.146066</y5>
			<x6>361.402567</x6>
			<y6>310.754925</y6>
			<x7>379.39723</x7>
			<y7>296.77401199999997</y7>
			<x8>385.881264</x8>
			<y8>304.876458</y8>
			<x9>380.522671</x9>
			<y9>318.837989</y9>
			<x10>369.819571</x10>
			<y10>322.748355</y10>
			<x11>359.008153</x11>
			<y11>317.248513</y11>
			<x12>368.103239</x12>
			<y12>337.677785</y12>
			<x13>386.467166</x13>
			<y13>353</y13>
			<x14>452.156209</x14>
			<y14>353</y14>
			<x15>466.885243</x15>
			<y15>349.978838</y15>
			<x16>468.27594799999997</x16>
			<y16>346.285519</y16>
			<x17>465.33994</x17>
			<y17>305.728068</y17>
			<x18>469.443644</x18>
			<y18>296.3114</y18>
			<x19>463.305694</x19>
			<y19>280.420528</y19>
			<x20>453.972844</x20>
			<y20>277.189888</y20>
			<x21>458.300228</x21>
			<y21>274.587285</y21>
			<x22>449.22627</x22>
			<y22>218.138963</y22>
			<x23>457.20295699999997</x23>
			<y23>204.497911</y23>
			<x24>454.617836</x24>
			<y24>190</y24>
			<x25>337</x25>
			<y25>190</y25>
		</polygon>
	</object>
</annotation>
