<annotation>
	<folder></folder>
	<filename>osorio_l8_jpg.rf.effb49f5f5b05653fc478f39b240d29c.jpg</filename>
	<path>osorio_l8_jpg.rf.effb49f5f5b05653fc478f39b240d29c.jpg</path>
	<source>
		<database>roboflow.com</database>
	</source>
	<size>
		<width>512</width>
		<height>384</height>
		<depth>3</depth>
	</size>
	<segmented>0</segmented>
	<object>
		<name>tanks</name>
		<pose>Unspecified</pose>
		<truncated>0</truncated>
		<difficult>0</difficult>
		<occluded>0</occluded>
		<bndbox>
			<xmin>1</xmin>
			<xmax>200</xmax>
			<ymin>1</ymin>
			<ymax>83</ymax>
		</bndbox>
		<polygon>
			<x1>199</x1>
			<y1>0</y1>
			<x2>11.339414</x2>
			<y2>0</y2>
			<x3>10.213007</x3>
			<y3>4.674006</y3>
			<x4>0.812696</x4>
			<y4>8.071349</y4>
			<x5>0</x5>
			<y5>8.061495</y5>
			<x6>0</x6>
			<y6>59.72909</y6>
			<x7>2.216986</x7>
			<y7>62.108758</y7>
			<x8>9.622129</x8>
			<y8>62.603701</y8>
			<x9>19.949039</x9>
			<y9>56.651625</y9>
			<x10>30.059168</x10>
			<y10>59.34018</y10>
			<x11>61.525268</x11>
			<y11>77.143288</y11>
			<x12>79.788601</x12>
			<y12>82</y12>
			<x13>100.073079</x13>
			<y13>82</y13>
			<x14>127.885793</x14>
			<y14>81.210276</y14>
			<x15>175.499697</x15>
			<y15>76.475631</y15>
			<x16>192.688371</x16>
			<y16>67.794545</y16>
			<x17>199</x17>
			<y17>67.349741</y17>
			<x18>199</x18>
			<y18>0</y18>
		</polygon>
	</object>
	<object>
		<name>tanks</name>
		<pose>Unspecified</pose>
		<truncated>0</truncated>
		<difficult>0</difficult>
		<occluded>0</occluded>
		<bndbox>
			<xmin>352</xmin>
			<xmax>512</xmax>
			<ymin>1</ymin>
			<ymax>99</ymax>
		</bndbox>
		<polygon>
			<x1>445.593251</x1>
			<y1>0</y1>
			<x2>477.400388</x2>
			<y2>14.045321</y2>
			<x3>465.250362</x3>
			<y3>26.117076</y3>
			<x4>473.614517</x4>
			<y4>39.632931</y4>
			<x5>470.496341</x5>
			<y5>48.474738</y5>
			<x6>412.152013</x6>
			<y6>57.047231</y6>
			<x7>382.410509</x7>
			<y7>53.283571</y7>
			<x8>357.62768</x8>
			<y8>57.22936</y8>
			<x9>351.326667</x9>
			<y9>69.116687</y9>
			<x10>351.326667</x10>
			<y10>80.273255</y10>
			<x11>353.788781</x11>
			<y11>96.739544</y11>
			<x12>354.737805</x12>
			<y12>98.473404</y12>
			<x13>371.22337</x13>
			<y13>98.473404</y13>
			<x14>383.41739</x14>
			<y14>97.527579</y14>
			<x15>389.945633</x15>
			<y15>95.192965</y15>
			<x16>437.60129</x16>
			<y16>91.496568</y16>
			<x17>444.216771</x17>
			<y17>92.811695</y17>
			<x18>488.530421</x18>
			<y18>89.374519</y18>
			<x19>489.168783</x19>
			<y19>88.508511</y19>
			<x20>493.33772</x20>
			<y20>89.001643</y20>
			<x21>511.150953</x21>
			<y21>87.619965</y21>
			<x22>511.479162</x22>
			<y22>43.615223</y22>
			<x23>506.243674</x23>
			<y23>8.600989</y23>
			<x24>499.9282</x24>
			<y24>7.745046</y24>
			<x25>482.454467</x25>
			<y25>0</y25>
			<x26>445.593251</x26>
			<y26>0</y26>
		</polygon>
	</object>
	<object>
		<name>tanks</name>
		<pose>Unspecified</pose>
		<truncated>0</truncated>
		<difficult>0</difficult>
		<occluded>0</occluded>
		<bndbox>
			<xmin>389</xmin>
			<xmax>513</xmax>
			<ymin>154</ymin>
			<ymax>307</ymax>
		</bndbox>
		<polygon>
			<x1>512</x1>
			<y1>153</y1>
			<x2>413.632436</x2>
			<y2>153</y2>
			<x3>389.154846</x3>
			<y3>177.730682</y3>
			<x4>388</x4>
			<y4>179.181338</y4>
			<x5>388</x5>
			<y5>189.062828</y5>
			<x6>390.949346</x6>
			<y6>214.350149</y6>
			<x7>393.559371</x7>
			<y7>222.47596299999998</y7>
			<x8>411.741858</x8>
			<y8>238.741232</y8>
			<x9>416.666511</x9>
			<y9>253.038781</y9>
			<x10>437.78491199999996</x10>
			<y10>280.5133</y10>
			<x11>465.674141</x11>
			<y11>303.206971</y11>
			<x12>477.928551</x12>
			<y12>306</y12>
			<x13>479.726958</x13>
			<y13>306</y13>
			<x14>512</x14>
			<y14>302.79082600000004</y14>
			<x15>512</x15>
			<y15>153</y15>
		</polygon>
	</object>
	<object>
		<name>tanks</name>
		<pose>Unspecified</pose>
		<truncated>0</truncated>
		<difficult>0</difficult>
		<occluded>0</occluded>
		<bndbox>
			<xmin>210</xmin>
			<xmax>417</xmax>
			<ymin>154</ymin>
			<ymax>219</ymax>
		</bndbox>
		<polygon>
			<x1>217.572917</x1>
			<y1>153</y1>
			<x2>210.125</x2>
			<y2>157.46875</y2>
			<x3>208.5625</x3>
			<y3>165.28125</y3>
			<x4>218.71875</x4>
			<y4>177</y4>
			<x5>228.875</x5>
			<y5>179.34375</y5>
			<x6>231.21875</x6>
			<y6>197.3125</y6>
			<x7>246.84375</x7>
			<y7>208.25</y7>
			<x8>278.875</x8>
			<y8>218.40625</y8>
			<x9>392.15625</x9>
			<y9>214.5</y9>
			<x10>394.5</x10>
			<y10>201.21875</y10>
			<x11>391.375</x11>
			<y11>180.90625</y11>
			<x12>414.8125</x12>
			<y12>160.59375</y12>
			<x13>416.375</x13>
			<y13>154.34375</y13>
			<x14>414.58333300000004</x14>
			<y14>153</y14>
			<x15>289.8125</x15>
			<y15>153</y15>
			<x16>289.8125</x16>
			<y16>160.59375</y16>
			<x17>245.28125</x17>
			<y17>164.5</y17>
			<x18>234.34375</x18>
			<y18>153.5625</y18>
			<x19>232.09375</x19>
			<y19>153</y19>
			<x20>217.572917</x20>
			<y20>153</y20>
		</polygon>
	</object>
</annotation>
