<annotation>
	<folder></folder>
	<filename>pt76_l4_jpg.rf.03da009d1bb6331e65438819e6b67216.jpg</filename>
	<path>pt76_l4_jpg.rf.03da009d1bb6331e65438819e6b67216.jpg</path>
	<source>
		<database>roboflow.com</database>
	</source>
	<size>
		<width>512</width>
		<height>384</height>
		<depth>3</depth>
	</size>
	<segmented>0</segmented>
	<object>
		<name>tanks</name>
		<pose>Unspecified</pose>
		<truncated>0</truncated>
		<difficult>0</difficult>
		<occluded>0</occluded>
		<bndbox>
			<xmin>95</xmin>
			<xmax>244</xmax>
			<ymin>2</ymin>
			<ymax>180</ymax>
		</bndbox>
		<polygon>
			<x1>138.52913</x1>
			<y1>179.1</y1>
			<x2>178.481375</x2>
			<y2>179.1</y2>
			<x3>242.573333</x3>
			<y3>161.891082</y3>
			<x4>242.573333</x4>
			<y4>147.7182</y4>
			<x5>198.066346</x5>
			<y5>36.655831</y5>
			<x6>191.264263</x6>
			<y6>34.086369</y6>
			<x7>172.424018</x7>
			<y7>4.199959</y7>
			<x8>170.975246</x8>
			<y8>0.584702</y8>
			<x9>141.804773</x9>
			<y9>0.869316</y9>
			<x10>94.453333</x10>
			<y10>13.583345</y10>
			<x11>94.453333</x11>
			<y11>14.478787</y11>
			<x12>107.015122</x12>
			<y12>100.460202</y12>
			<x13>138.52913</x13>
			<y13>179.1</y13>
		</polygon>
	</object>
	<object>
		<name>tanks</name>
		<pose>Unspecified</pose>
		<truncated>0</truncated>
		<difficult>0</difficult>
		<occluded>0</occluded>
		<bndbox>
			<xmin>334</xmin>
			<xmax>513</xmax>
			<ymin>1</ymin>
			<ymax>180</ymax>
		</bndbox>
		<polygon>
			<x1>394.258024</x1>
			<y1>0</y1>
			<x2>333</x2>
			<y2>19.615759</y2>
			<x3>333</x3>
			<y3>23.081939</y3>
			<x4>333.65435</x4>
			<y4>29.144272</y4>
			<x5>370.435865</x5>
			<y5>138.605536</y5>
			<x6>379.376141</x6>
			<y6>151.425257</y6>
			<x7>395.376591</x7>
			<y7>160.489962</y7>
			<x8>415.102568</x8>
			<y8>179</y8>
			<x9>425.246008</x9>
			<y9>179</y9>
			<x10>512</x10>
			<y10>151.220043</y10>
			<x11>512</x11>
			<y11>125.644107</y11>
			<x12>469.78067599999997</x12>
			<y12>0</y12>
			<x13>394.258024</x13>
			<y13>0</y13>
		</polygon>
	</object>
	<object>
		<name>tanks</name>
		<pose>Unspecified</pose>
		<truncated>0</truncated>
		<difficult>0</difficult>
		<occluded>0</occluded>
		<bndbox>
			<xmin>27</xmin>
			<xmax>175</xmax>
			<ymin>181</ymin>
			<ymax>358</ymax>
		</bndbox>
		<polygon>
			<x1>25.930047</x1>
			<y1>180</y1>
			<x2>32.315071</x2>
			<y2>199.00174</y2>
			<x3>39.294672</x3>
			<y3>203.648383</y3>
			<x4>43.971213</x4>
			<y4>217.565705</y4>
			<x5>40.192818</x5>
			<y5>222.44580200000001</y5>
			<x6>40.916568</x6>
			<y6>224.599673</y6>
			<x7>45.354857</x7>
			<y7>228.13323</y7>
			<x8>50.031399</x8>
			<y8>242.05055099999998</y8>
			<x9>47.430323</x9>
			<y9>243.984515</y9>
			<x10>51.037941</x10>
			<y10>254.720735</y10>
			<x11>59.289506</x11>
			<y11>256.702905</y11>
			<x12>64.634125</x12>
			<y12>272.60841600000003</y12>
			<x13>70.551845</x13>
			<y13>277.319825</y13>
			<x14>75.228387</x14>
			<y14>291.237146</y14>
			<x15>74.082187</x15>
			<y15>313.625353</y15>
			<x16>81.288572</x16>
			<y16>315.721993</y16>
			<x17>84.62896</x17>
			<y17>325.662938</y17>
			<x18>110.972146</x18>
			<y18>352.461327</y18>
			<x19>117.594824</x19>
			<y19>357</y19>
			<x20>127.744784</x20>
			<y20>357</y20>
			<x21>149.466705</x21>
			<y21>350.044308</y21>
			<x22>132.116413</x22>
			<y22>292.839787</y22>
			<x23>133.381335</x23>
			<y23>286.929447</y23>
			<x24>141.232053</x24>
			<y24>287.718702</y24>
			<x25>171.010603</x25>
			<y25>337.640328</y25>
			<x26>174</x26>
			<y26>336.935244</y26>
			<x27>174</x27>
			<y27>320.737448</y27>
			<x28>126.708964</x28>
			<y28>180</y28>
			<x29>25.930047</x29>
			<y29>180</y29>
		</polygon>
	</object>
	<object>
		<name>tanks</name>
		<pose>Unspecified</pose>
		<truncated>0</truncated>
		<difficult>0</difficult>
		<occluded>0</occluded>
		<bndbox>
			<xmin>323</xmin>
			<xmax>493</xmax>
			<ymin>181</ymin>
			<ymax>385</ymax>
		</bndbox>
		<polygon>
			<x1>322</x1>
			<y1>180</y1>
			<x2>322</x2>
			<y2>384</y2>
			<x3>382.487939</x3>
			<y3>384</y3>
			<x4>491.98928</x4>
			<y4>348.935992</y4>
			<x5>491.98928</x5>
			<y5>329.116377</y5>
			<x6>441.88273100000004</x6>
			<y6>180</y6>
			<x7>322</x7>
			<y7>180</y7>
		</polygon>
	</object>
</annotation>
