<annotation>
	<folder></folder>
	<filename>t72m2_moderna_l1_jpg.rf.73d8e456e8d58d132d947b1ddc16d400.jpg</filename>
	<path>t72m2_moderna_l1_jpg.rf.73d8e456e8d58d132d947b1ddc16d400.jpg</path>
	<source>
		<database>roboflow.com</database>
	</source>
	<size>
		<width>512</width>
		<height>330</height>
		<depth>3</depth>
	</size>
	<segmented>0</segmented>
	<object>
		<name>tanks</name>
		<pose>Unspecified</pose>
		<truncated>0</truncated>
		<difficult>0</difficult>
		<occluded>0</occluded>
		<bndbox>
			<xmin>1</xmin>
			<xmax>111</xmax>
			<ymin>1</ymin>
			<ymax>119</ymax>
		</bndbox>
		<polygon>
			<x1>0</x1>
			<y1>0</y1>
			<x2>0</x2>
			<y2>117.783022</y2>
			<x3>0.138031</x3>
			<y3>118</y3>
			<x4>104.789642</x4>
			<y4>118</y4>
			<x5>110</x5>
			<y5>107.168434</y5>
			<x6>110</x6>
			<y6>46.341884</y6>
			<x7>98.145435</x7>
			<y7>6.560365</y7>
			<x8>92.951724</x8>
			<y8>0</y8>
			<x9>0</x9>
			<y9>0</y9>
		</polygon>
	</object>
	<object>
		<name>tanks</name>
		<pose>Unspecified</pose>
		<truncated>0</truncated>
		<difficult>0</difficult>
		<occluded>0</occluded>
		<bndbox>
			<xmin>244</xmin>
			<xmax>373</xmax>
			<ymin>1</ymin>
			<ymax>119</ymax>
		</bndbox>
		<polygon>
			<x1>243.338708</x1>
			<y1>0</y1>
			<x2>278.501735</x2>
			<y2>118</y2>
			<x3>372</x3>
			<y3>118</y3>
			<x4>372</x4>
			<y4>61.252576</y4>
			<x5>367.40339800000004</x5>
			<y5>53.16738</y5>
			<x6>371.308384</x6>
			<y6>43.844781</y6>
			<x7>369.025496</x7>
			<y7>30.577137</y7>
			<x8>356.560771</x8>
			<y8>5.568248</y8>
			<x9>357.99659399999996</x9>
			<y9>0</y9>
			<x10>243.338708</x10>
			<y10>0</y10>
		</polygon>
	</object>
	<object>
		<name>tanks</name>
		<pose>Unspecified</pose>
		<truncated>0</truncated>
		<difficult>0</difficult>
		<occluded>0</occluded>
		<bndbox>
			<xmin>1</xmin>
			<xmax>162</xmax>
			<ymin>122</ymin>
			<ymax>211</ymax>
		</bndbox>
		<polygon>
			<x1>0</x1>
			<y1>168.529686</y1>
			<x2>13.559628</x2>
			<y2>177.109761</y2>
			<x3>3.119736</x3>
			<y3>186.89550400000002</y3>
			<x4>10.004687</x4>
			<y4>210</y4>
			<x5>39.35374</x5>
			<y5>210</y5>
			<x6>60.489767</x6>
			<y6>205.91565300000002</y6>
			<x7>69.850855</x7>
			<y7>196.335087</y7>
			<x8>106.642663</x8>
			<y8>185.341238</y8>
			<x9>116.535186</x9>
			<y9>173.718637</y9>
			<x10>125.555862</x10>
			<y10>171.975472</y10>
			<x11>146.982703</x11>
			<y11>154.239804</y11>
			<x12>159.064079</x12>
			<y12>149.962555</y12>
			<x13>161</x13>
			<y13>145.471809</y13>
			<x14>161</x14>
			<y14>128.983997</y14>
			<x15>158.475073</x15>
			<y15>120.51085</y15>
			<x16>152.578735</x16>
			<y16>124.996856</y16>
			<x17>140.578578</x17>
			<y17>126.344462</y17>
			<x18>143.233582</x18>
			<y18>138.456314</y18>
			<x19>135.77317</x19>
			<y19>148.637616</y19>
			<x20>128.557036</x20>
			<y20>150.032069</y20>
			<x21>130.523307</x21>
			<y21>143.825309</y21>
			<x22>107.070361</x22>
			<y22>148.357379</y22>
			<x23>110.515681</x23>
			<y23>153.518399</y23>
			<x24>114.752336</x24>
			<y24>151.728387</y24>
			<x25>116.312601</x25>
			<y25>160.166524</y25>
			<x26>96.467723</x26>
			<y26>164.001368</y26>
			<x27>59.616081</x27>
			<y27>155.584859</y27>
			<x28>43.378248</x28>
			<y28>158.72267399999998</y28>
			<x29>36.405371</x29>
			<y29>151.330474</y29>
			<x30>37.744075</x30>
			<y30>146.216301</y30>
			<x31>23.229566</x31>
			<y31>151.935046</y31>
			<x32>4.722372</x32>
			<y32>150.655914</y32>
			<x33>0</x33>
			<y33>152.943268</y33>
			<x34>0</x34>
			<y34>168.529686</y34>
		</polygon>
	</object>
	<object>
		<name>tanks</name>
		<pose>Unspecified</pose>
		<truncated>0</truncated>
		<difficult>0</difficult>
		<occluded>0</occluded>
		<bndbox>
			<xmin>175</xmin>
			<xmax>258</xmax>
			<ymin>119</ymin>
			<ymax>312</ymax>
		</bndbox>
		<polygon>
			<x1>174</x1>
			<y1>118</y1>
			<x2>174</x2>
			<y2>311</y2>
			<x3>190.07157</x3>
			<y3>311</y3>
			<x4>212.302371</x4>
			<y4>306.704098</y4>
			<x5>212.27610099999998</x5>
			<y5>292.94161099999997</y5>
			<x6>226.506292</x6>
			<y6>286.894606</y6>
			<x7>240.361897</x7>
			<y7>268.83043599999996</y7>
			<x8>257</x8>
			<y8>234.380472</y8>
			<x9>257</x9>
			<y9>197.172</y9>
			<x10>255.767676</x10>
			<y10>187.820862</y10>
			<x11>257</x11>
			<y11>178.535078</y11>
			<x12>257</x12>
			<y12>156.089197</y12>
			<x13>254.106155</x13>
			<y13>146.378037</y13>
			<x14>257</x14>
			<y14>133.186695</y14>
			<x15>257</x15>
			<y15>118</y15>
			<x16>174</x16>
			<y16>118</y16>
		</polygon>
	</object>
</annotation>
