<annotation>
	<folder></folder>
	<filename>t80bvm_l3_jpg.rf.368f5db99bd86075c66149903fb4a851.jpg</filename>
	<path>t80bvm_l3_jpg.rf.368f5db99bd86075c66149903fb4a851.jpg</path>
	<source>
		<database>roboflow.com</database>
	</source>
	<size>
		<width>512</width>
		<height>356</height>
		<depth>3</depth>
	</size>
	<segmented>0</segmented>
	<object>
		<name>tanks</name>
		<pose>Unspecified</pose>
		<truncated>0</truncated>
		<difficult>0</difficult>
		<occluded>0</occluded>
		<bndbox>
			<xmin>243</xmin>
			<xmax>379</xmax>
			<ymin>46</ymin>
			<ymax>171</ymax>
		</bndbox>
		<polygon>
			<x1>378</x1>
			<y1>170</y1>
			<x2>378</x2>
			<y2>49.408859</y2>
			<x3>346.664075</x3>
			<y3>44.756216</y3>
			<x4>325.449568</x4>
			<y4>44.756216</y4>
			<x5>323.069741</x5>
			<y5>53.264303</y5>
			<x6>326.318509</x6>
			<y6>58.114408</y6>
			<x7>323.479113</x7>
			<y7>76.255724</y7>
			<x8>242.938487</x8>
			<y8>66.348057</y8>
			<x9>241.818064</x9>
			<y9>71.542345</y9>
			<x10>241.818064</x10>
			<y10>74.133959</y10>
			<x11>287.90357</x11>
			<y11>81.89295</y11>
			<x12>295.669741</x12>
			<y12>90.689589</y12>
			<x13>293.743245</x13>
			<y13>104.598708</y13>
			<x14>299.072842</x14>
			<y14>109.757768</y14>
			<x15>313.282918</x15>
			<y15>108.591823</y15>
			<x16>310.34282</x16>
			<y16>132.177863</y16>
			<x17>316.840352</x17>
			<y17>141.878073</y17>
			<x18>310.774376</x18>
			<y18>170</y18>
			<x19>378</x19>
			<y19>170</y19>
		</polygon>
	</object>
	<object>
		<name>tanks</name>
		<pose>Unspecified</pose>
		<truncated>0</truncated>
		<difficult>0</difficult>
		<occluded>0</occluded>
		<bndbox>
			<xmin>447</xmin>
			<xmax>513</xmax>
			<ymin>1</ymin>
			<ymax>171</ymax>
		</bndbox>
		<polygon>
			<x1>512</x1>
			<y1>170</y1>
			<x2>512</x2>
			<y2>0</y2>
			<x3>449.838587</x3>
			<y3>0</y3>
			<x4>449.130291</x4>
			<y4>4.452241</y4>
			<x5>455.691409</x5>
			<y5>14.109116</y5>
			<x6>451.363952</x6>
			<y6>74.245534</y6>
			<x7>463.299599</x7>
			<y7>89.041754</y7>
			<x8>462.671426</x8>
			<y8>101.972544</y8>
			<x9>446.059356</x9>
			<y9>168.967694</y9>
			<x10>445.978459</x10>
			<y10>170</y10>
			<x11>476.091149</x11>
			<y11>170</y11>
			<x12>477.1897</x12>
			<y12>164.907106</y12>
			<x13>504.865003</x13>
			<y13>166.845557</y13>
			<x14>507.79445699999997</x14>
			<y14>170</y14>
			<x15>512</x15>
			<y15>170</y15>
		</polygon>
	</object>
	<object>
		<name>tanks</name>
		<pose>Unspecified</pose>
		<truncated>0</truncated>
		<difficult>0</difficult>
		<occluded>0</occluded>
		<bndbox>
			<xmin>120</xmin>
			<xmax>366</xmax>
			<ymin>171</ymin>
			<ymax>357</ymax>
		</bndbox>
		<polygon>
			<x1>174.945498</x1>
			<y1>170</y1>
			<x2>161.09925</x2>
			<y2>252.72315600000002</y2>
			<x3>203.582721</x3>
			<y3>260.116709</y3>
			<x4>211.648502</x4>
			<y4>252.62815799999998</y4>
			<x5>217.898805</x5>
			<y5>253.55617999999998</y5>
			<x6>226.139586</x6>
			<y6>260.208571</y6>
			<x7>225.953674</x7>
			<y7>271.038628</y7>
			<x8>189.069811</x8>
			<y8>302.478295</y8>
			<x9>179.828334</x9>
			<y9>305.44921899999997</y9>
			<x10>175.475554</x10>
			<y10>315.660595</y10>
			<x11>163.696773</x11>
			<y11>320.426322</y11>
			<x12>157.260557</x12>
			<y12>330.328357</y12>
			<x13>144.213125</x13>
			<y13>335.991484</y13>
			<x14>119.365773</x14>
			<y14>356</y14>
			<x15>169.069063</x15>
			<y15>356</y15>
			<x16>170.65799</x16>
			<y16>352.947113</y16>
			<x17>183.612466</x17>
			<y17>352.69901400000003</y17>
			<x18>193.039855</x18>
			<y18>338.898032</y18>
			<x19>205.540462</x19>
			<y19>340.754076</y19>
			<x20>210.708026</x20>
			<y20>331.74944300000004</y20>
			<x21>244.053889</x21>
			<y21>311.727894</y21>
			<x22>246.312324</x22>
			<y22>326.178176</y22>
			<x23>252.830583</x23>
			<y23>335.832113</y23>
			<x24>252.240834</x24>
			<y24>356</y24>
			<x25>324.810997</x25>
			<y25>356</y25>
			<x26>364.931704</x26>
			<y26>170</y26>
			<x27>252.405795</x27>
			<y27>170</y27>
			<x28>250.358754</x28>
			<y28>187.800919</y28>
			<x29>242.025017</x29>
			<y29>186.563557</y29>
			<x30>247.509695</x30>
			<y30>170</y30>
			<x31>174.945498</x31>
			<y31>170</y31>
		</polygon>
	</object>
	<object>
		<name>tanks</name>
		<pose>Unspecified</pose>
		<truncated>0</truncated>
		<difficult>0</difficult>
		<occluded>0</occluded>
		<bndbox>
			<xmin>379</xmin>
			<xmax>513</xmax>
			<ymin>171</ymin>
			<ymax>354</ymax>
		</bndbox>
		<polygon>
			<x1>512</x1>
			<y1>174.540689</y1>
			<x2>482.38028099999997</x2>
			<y2>170.142863</y2>
			<x3>448.30796</x3>
			<y3>170.142863</y3>
			<x4>441.932156</x4>
			<y4>205.470665</y4>
			<x5>438.848419</x5>
			<y5>213.906555</y5>
			<x6>423.464582</x6>
			<y6>223.69251500000001</y6>
			<x7>415.318732</x7>
			<y7>226.29466</y7>
			<x8>388.371707</x8>
			<y8>222.293665</y8>
			<x9>378</x9>
			<y9>227.020267</y9>
			<x10>378</x10>
			<y10>272.742597</y10>
			<x11>391.163335</x11>
			<y11>262.09478</y11>
			<x12>410.923826</x12>
			<y12>270.11089</y12>
			<x13>412.156989</x13>
			<y13>284.905152</y13>
			<x14>422.974969</x14>
			<y14>299.21673</y14>
			<x15>415.051521</x15>
			<y15>318.368865</y15>
			<x16>415.642377</x16>
			<y16>327.350347</y16>
			<x17>410.374462</x17>
			<y17>334.19140500000003</y17>
			<x18>426.194803</x18>
			<y18>342.893033</y18>
			<x19>428.846687</x19>
			<y19>353</y19>
			<x20>438.559427</x20>
			<y20>353</y20>
			<x21>505.75813700000003</x21>
			<y21>349.87017000000003</y21>
			<x22>512</x22>
			<y22>320.93282999999997</y22>
			<x23>512</x23>
			<y23>174.540689</y23>
		</polygon>
	</object>
</annotation>
