<annotation>
	<folder></folder>
	<filename>t90ms_tagil_l1_jpg.rf.89bb32fad80508fd92dd4c8303aeba1d.jpg</filename>
	<path>t90ms_tagil_l1_jpg.rf.89bb32fad80508fd92dd4c8303aeba1d.jpg</path>
	<source>
		<database>roboflow.com</database>
	</source>
	<size>
		<width>512</width>
		<height>341</height>
		<depth>3</depth>
	</size>
	<segmented>0</segmented>
	<object>
		<name>tanks</name>
		<pose>Unspecified</pose>
		<truncated>0</truncated>
		<difficult>0</difficult>
		<occluded>0</occluded>
		<bndbox>
			<xmin>94</xmin>
			<xmax>313</xmax>
			<ymin>1</ymin>
			<ymax>164</ymax>
		</bndbox>
		<polygon>
			<x1>312</x1>
			<y1>163</y1>
			<x2>312</x2>
			<y2>0</y2>
			<x3>92.801318</x3>
			<y3>0</y3>
			<x4>104.767311</x4>
			<y4>92.381015</y4>
			<x5>144.688714</x5>
			<y5>163</y5>
			<x6>312</x6>
			<y6>163</y6>
		</polygon>
	</object>
	<object>
		<name>tanks</name>
		<pose>Unspecified</pose>
		<truncated>0</truncated>
		<difficult>0</difficult>
		<occluded>0</occluded>
		<bndbox>
			<xmin>364</xmin>
			<xmax>513</xmax>
			<ymin>1</ymin>
			<ymax>164</ymax>
		</bndbox>
		<polygon>
			<x1>512</x1>
			<y1>163</y1>
			<x2>512</x2>
			<y2>0</y2>
			<x3>363.029378</x3>
			<y3>0</y3>
			<x4>367.326658</x4>
			<y4>7.696258</y4>
			<x5>377.996017</x5>
			<y5>22.938215</y5>
			<x6>384.911226</x6>
			<y6>25.979173</y6>
			<x7>389.208784</x7>
			<y7>42.375428</y7>
			<x8>406.249947</x8>
			<y8>56.463087</y8>
			<x9>418.277823</x9>
			<y9>82.193184</y9>
			<x10>427.588668</x10>
			<y10>86.947003</y10>
			<x11>432.973037</x11>
			<y11>111.733771</y11>
			<x12>451.051322</x12>
			<y12>117.046153</y12>
			<x13>449.470795</x13>
			<y13>121.626174</y13>
			<x14>466.511957</x14>
			<y14>135.713833</y14>
			<x15>466.40094999999997</x15>
			<y15>143.247914</y15>
			<x16>471.414238</x16>
			<y16>131.605475</y16>
			<x17>473.427166</x17>
			<y17>138.754789</y17>
			<x18>480.342373</x18>
			<y18>141.795747</y18>
			<x19>480.392064</x19>
			<y19>158.961535</y19>
			<x20>482.514607</x20>
			<y20>163</y20>
			<x21>512</x21>
			<y21>163</y21>
		</polygon>
	</object>
	<object>
		<name>tanks</name>
		<pose>Unspecified</pose>
		<truncated>0</truncated>
		<difficult>0</difficult>
		<occluded>0</occluded>
		<bndbox>
			<xmin>195</xmin>
			<xmax>311</xmax>
			<ymin>211</ymin>
			<ymax>271</ymax>
		</bndbox>
		<polygon>
			<x1>248.916175</x1>
			<y1>269.609626</y1>
			<x2>283.282056</x2>
			<y2>265.184117</y2>
			<x3>297.549529</x3>
			<y3>255.470943</y3>
			<x4>296.709339</x4>
			<y4>236.31497000000002</y4>
			<x5>307.039132</x5>
			<y5>223.907999</y5>
			<x6>309.585649</x6>
			<y6>222.962599</y6>
			<x7>307.214322</x7>
			<y7>209.948768</y7>
			<x8>194.16309</x8>
			<y8>224.507077</y8>
			<x9>194.16309</x9>
			<y9>245.984437</y9>
			<x10>198.467975</x10>
			<y10>269.609626</y10>
			<x11>248.916175</x11>
			<y11>269.609626</y11>
		</polygon>
	</object>
	<object>
		<name>tanks</name>
		<pose>Unspecified</pose>
		<truncated>0</truncated>
		<difficult>0</difficult>
		<occluded>0</occluded>
		<bndbox>
			<xmin>313</xmin>
			<xmax>513</xmax>
			<ymin>164</ymin>
			<ymax>341</ymax>
		</bndbox>
		<polygon>
			<x1>343.386291</x1>
			<y1>163</y1>
			<x2>347.808199</x2>
			<y2>181.592847</y2>
			<x3>340.343606</x3>
			<y3>218.007445</y3>
			<x4>341.708977</x4>
			<y4>228.548507</y4>
			<x5>350.49703</x5>
			<y5>233.699244</y5>
			<x6>342.669129</x6>
			<y6>241.185807</y6>
			<x7>312</x7>
			<y7>252.82909999999998</y7>
			<x8>312</x8>
			<y8>320.926073</y8>
			<x9>314.470621</x9>
			<y9>340</y9>
			<x10>320.484688</x10>
			<y10>340</y10>
			<x11>324.029108</x11>
			<y11>337.61262</y11>
			<x12>362.721486</x12>
			<y12>333.300315</y12>
			<x13>377.07042</x13>
			<y13>340</y13>
			<x14>441.685788</x14>
			<y14>340</y14>
			<x15>452.221881</x15>
			<y15>334.61782900000003</y15>
			<x16>480.803756</x16>
			<y16>325.394359</y16>
			<x17>491.574979</x17>
			<y17>309.283285</y17>
			<x18>497.67420100000004</x18>
			<y18>262.327621</y18>
			<x19>504.008981</x19>
			<y19>253.76299799999998</y19>
			<x20>512</x20>
			<y20>258.287981</y20>
			<x21>512</x21>
			<y21>242.735615</y21>
			<x22>501.67195000000004</x22>
			<y22>163</y22>
			<x23>343.386291</x23>
			<y23>163</y23>
		</polygon>
	</object>
</annotation>
