<annotation>
	<folder></folder>
	<filename>tm_800_l2_jpg.rf.4f904cd07f1bb30b3da21509bbc01c58.jpg</filename>
	<path>tm_800_l2_jpg.rf.4f904cd07f1bb30b3da21509bbc01c58.jpg</path>
	<source>
		<database>roboflow.com</database>
	</source>
	<size>
		<width>512</width>
		<height>341</height>
		<depth>3</depth>
	</size>
	<segmented>0</segmented>
	<object>
		<name>tanks</name>
		<pose>Unspecified</pose>
		<truncated>0</truncated>
		<difficult>0</difficult>
		<occluded>0</occluded>
		<bndbox>
			<xmin>1</xmin>
			<xmax>216</xmax>
			<ymin>1</ymin>
			<ymax>174</ymax>
		</bndbox>
		<polygon>
			<x1>0</x1>
			<y1>173</y1>
			<x2>215</x2>
			<y2>173</y2>
			<x3>215</x3>
			<y3>0</y3>
			<x4>0</x4>
			<y4>0</y4>
			<x5>0</x5>
			<y5>173</y5>
		</polygon>
	</object>
	<object>
		<name>tanks</name>
		<pose>Unspecified</pose>
		<truncated>0</truncated>
		<difficult>0</difficult>
		<occluded>0</occluded>
		<bndbox>
			<xmin>321</xmin>
			<xmax>509</xmax>
			<ymin>1</ymin>
			<ymax>109</ymax>
		</bndbox>
		<polygon>
			<x1>462.19236</x1>
			<y1>0</y1>
			<x2>450.54517899999996</x2>
			<y2>2.561467</y2>
			<x3>444.37739899999997</x3>
			<y3>36.070552</y3>
			<x4>426.56057699999997</x4>
			<y4>36.549777</y4>
			<x5>374.0014</x5>
			<y5>58.207559</y5>
			<x6>335.979782</x6>
			<y6>62.802724</y6>
			<x7>319.750577</x7>
			<y7>105.293944</y7>
			<x8>319.890498</x8>
			<y8>108.468254</y8>
			<x9>356.641263</x9>
			<y9>108.468254</y9>
			<x10>503.125524</x10>
			<y10>104.528216</y10>
			<x11>507.545</x11>
			<y11>104.337898</y11>
			<x12>507.545</x12>
			<y12>0</y12>
			<x13>462.19236</x13>
			<y13>0</y13>
		</polygon>
	</object>
	<object>
		<name>tanks</name>
		<pose>Unspecified</pose>
		<truncated>0</truncated>
		<difficult>0</difficult>
		<occluded>0</occluded>
		<bndbox>
			<xmin>63</xmin>
			<xmax>216</xmax>
			<ymin>174</ymin>
			<ymax>328</ymax>
		</bndbox>
		<polygon>
			<x1>215</x1>
			<y1>173</y1>
			<x2>103.257661</x2>
			<y2>173</y2>
			<x3>86.634483</x3>
			<y3>203.089272</y3>
			<x4>87.784886</x4>
			<y4>214.02119</y4>
			<x5>75.363568</x5>
			<y5>222.265651</y5>
			<x6>61.598051</x6>
			<y6>291.400119</y6>
			<x7>62.048353</x7>
			<y7>295.679186</y7>
			<x8>77.320774</x8>
			<y8>304.004498</y8>
			<x9>78.471178</x9>
			<y9>314.936416</y9>
			<x10>84.50953</x10>
			<y10>319.700161</y10>
			<x11>95.43583</x11>
			<y11>318.29573500000004</y11>
			<x12>122.825268</x12>
			<y12>327</y12>
			<x13>130.156713</x13>
			<y13>327</y13>
			<x14>210.219753</x14>
			<y14>314.621623</y14>
			<x15>215</x15>
			<y15>314.783002</y15>
			<x16>215</x16>
			<y16>173</y16>
		</polygon>
	</object>
	<object>
		<name>tanks</name>
		<pose>Unspecified</pose>
		<truncated>0</truncated>
		<difficult>0</difficult>
		<occluded>0</occluded>
		<bndbox>
			<xmin>376</xmin>
			<xmax>513</xmax>
			<ymin>198</ymin>
			<ymax>342</ymax>
		</bndbox>
		<polygon>
			<x1>512</x1>
			<y1>341</y1>
			<x2>512</x2>
			<y2>196.912752</y2>
			<x3>480.821384</x3>
			<y3>196.912752</y3>
			<x4>464.63475700000004</x4>
			<y4>206.954433</y4>
			<x5>432.33313499999997</x5>
			<y5>216.397976</y5>
			<x6>427.455154</x6>
			<y6>223.342964</y6>
			<x7>410.34134</x7>
			<y7>225.541596</y7>
			<x8>389.52024700000004</x8>
			<y8>242.304624</y8>
			<x9>381.48258899999996</x9>
			<y9>256.144612</y9>
			<x10>375.44890799999996</x10>
			<y10>284.798299</y10>
			<x11>375.787014</x11>
			<y11>293.094342</y11>
			<x12>379.84604</x12>
			<y12>300.412257</y12>
			<x13>380.538371</x13>
			<y13>317.399822</y13>
			<x14>396.99956</x14>
			<y14>341</y14>
			<x15>512</x15>
			<y15>341</y15>
		</polygon>
	</object>
</annotation>
