<annotation>
	<folder></folder>
	<filename>type_74_l2_jpg.rf.ae79a84ef7900d12c98c0c2f9abc2718.jpg</filename>
	<path>type_74_l2_jpg.rf.ae79a84ef7900d12c98c0c2f9abc2718.jpg</path>
	<source>
		<database>roboflow.com</database>
	</source>
	<size>
		<width>512</width>
		<height>384</height>
		<depth>3</depth>
	</size>
	<segmented>0</segmented>
	<object>
		<name>tanks</name>
		<pose>Unspecified</pose>
		<truncated>0</truncated>
		<difficult>0</difficult>
		<occluded>0</occluded>
		<bndbox>
			<xmin>308</xmin>
			<xmax>492</xmax>
			<ymin>1</ymin>
			<ymax>193</ymax>
		</bndbox>
		<polygon>
			<x1>307</x1>
			<y1>0</y1>
			<x2>307</x2>
			<y2>138.181094</y2>
			<x3>327.584839</x3>
			<y3>189.38871</y3>
			<x4>402.36240399999997</x4>
			<y4>192</y4>
			<x5>421.61805</x5>
			<y5>192</y5>
			<x6>441.506493</x6>
			<y6>186.07523</y6>
			<x7>438.292725</x7>
			<y7>174.425739</y7>
			<x8>444.74253699999997</x8>
			<y8>163.442781</y8>
			<x9>438.42157599999996</x9>
			<y9>158.529626</y9>
			<x10>425.90851</x10>
			<y10>132.807203</y10>
			<x11>411.269678</x11>
			<y11>96.391097</y11>
			<x12>408.644684</x12>
			<y12>79.049965</y12>
			<x13>429.741418</x13>
			<y13>69.367161</y13>
			<x14>468.238918</x14>
			<y14>62.42953</y14>
			<x15>473.74660900000003</x15>
			<y15>65.319568</y15>
			<x16>490.751084</x16>
			<y16>59.711283</y16>
			<x17>490.751084</x17>
			<y17>45.745669</y17>
			<x18>475.00277</x18>
			<y18>46.822238</y18>
			<x19>452.15873799999997</x19>
			<y19>33.238972</y19>
			<x20>432.817394</x20>
			<y20>31.071896</y20>
			<x21>420.326869</x21>
			<y21>0</y21>
			<x22>411.856592</x22>
			<y22>0</y22>
			<x23>404.530096</x23>
			<y23>6.650533</y23>
			<x24>389.63356</x24>
			<y24>2.026654</y24>
			<x25>384.625096</x25>
			<y25>5.784066</y25>
			<x26>371.918752</x26>
			<y26>3.905815</y26>
			<x27>370.72038</x27>
			<y27>0</y27>
			<x28>307</x28>
			<y28>0</y28>
		</polygon>
	</object>
	<object>
		<name>tanks</name>
		<pose>Unspecified</pose>
		<truncated>0</truncated>
		<difficult>0</difficult>
		<occluded>0</occluded>
		<bndbox>
			<xmin>1</xmin>
			<xmax>104</xmax>
			<ymin>196</ymin>
			<ymax>385</ymax>
		</bndbox>
		<polygon>
			<x1>0</x1>
			<y1>195</y1>
			<x2>0</x2>
			<y2>384</y2>
			<x3>58.333775</x3>
			<y3>384</y3>
			<x4>62.64244</x4>
			<y4>382.716448</y4>
			<x5>53.918091</x5>
			<y5>362.654474</y5>
			<x6>68.71803</x6>
			<y6>360.57097899999997</y6>
			<x7>77.02349</x7>
			<y7>353.445965</y7>
			<x8>84.098073</x8>
			<y8>357.151966</y8>
			<x9>89.884483</x9>
			<y9>374.60104</y9>
			<x10>102.825559</x10>
			<y10>370.745892</y10>
			<x11>102.825559</x11>
			<y11>359.779771</y11>
			<x12>96.577607</x12>
			<y12>360.410536</y12>
			<x13>102.825559</x13>
			<y13>355.05059800000004</y13>
			<x14>102.825559</x14>
			<y14>343.763519</y14>
			<x15>99.69014</x15>
			<y15>329.253009</y15>
			<x16>102.825559</x16>
			<y16>322.034611</y16>
			<x17>102.825559</x17>
			<y17>320.033581</y17>
			<x18>97.652434</x18>
			<y18>301.955147</y18>
			<x19>98.971062</x19>
			<y19>294.121021</y19>
			<x20>74.928396</x20>
			<y20>234.311588</y20>
			<x21>73.51348</x21>
			<y21>233.57038699999998</y21>
			<x22>31.618105</x22>
			<y22>246.051025</y22>
			<x23>24.543522</x23>
			<y23>242.345024</y23>
			<x24>24.614197</x24>
			<y24>234.185044</y24>
			<x25>37.744508</x25>
			<y25>227.948115</y25>
			<x26>45.540542</x26>
			<y26>213.998634</y26>
			<x27>55.260919</x27>
			<y27>207.614822</y27>
			<x28>44.196301</x28>
			<y28>205.097454</y28>
			<x29>10.280997</x29>
			<y29>215.200827</y29>
			<x30>2.696987</x30>
			<y30>204.67036</y30>
			<x31>10.422346</x31>
			<y31>198.880863</y31>
			<x32>30.556564</x32>
			<y32>204.509917</y32>
			<x33>39.745746</x33>
			<y33>195</y33>
			<x34>0</x34>
			<y34>195</y34>
		</polygon>
	</object>
</annotation>
