<annotation>
	<folder></folder>
	<filename>type_74_l2_jpg.rf.aacf18cdf9593d88a1de711fa9823f59.jpg</filename>
	<path>type_74_l2_jpg.rf.aacf18cdf9593d88a1de711fa9823f59.jpg</path>
	<source>
		<database>roboflow.com</database>
	</source>
	<size>
		<width>512</width>
		<height>349</height>
		<depth>3</depth>
	</size>
	<segmented>0</segmented>
	<object>
		<name>tanks</name>
		<pose>Unspecified</pose>
		<truncated>0</truncated>
		<difficult>0</difficult>
		<occluded>0</occluded>
		<bndbox>
			<xmin>1</xmin>
			<xmax>232</xmax>
			<ymin>1</ymin>
			<ymax>178</ymax>
		</bndbox>
		<polygon>
			<x1>0</x1>
			<y1>0</y1>
			<x2>0</x2>
			<y2>48.254514</y2>
			<x3>5.096097</x3>
			<y3>58.726511</y3>
			<x4>16.106368</x4>
			<y4>69.415872</y4>
			<x5>31.151207</x5>
			<y5>106.841977</y5>
			<x6>29.335004</x6>
			<y6>119.024125</y6>
			<x7>42.708194</x7>
			<y7>152.291774</y7>
			<x8>41.814885</x8>
			<y8>154.346807</y8>
			<x9>48.052874</x9>
			<y9>169.864661</y9>
			<x10>55.899147</x10>
			<y10>173.97261</y10>
			<x11>54.583159</x11>
			<y11>177</y11>
			<x12>230.947707</x12>
			<y12>177</y12>
			<x13>230.947707</x13>
			<y13>169.657975</y13>
			<x14>162.747263</x14>
			<y14>0</y14>
			<x15>0</x15>
			<y15>0</y15>
		</polygon>
	</object>
	<object>
		<name>tanks</name>
		<pose>Unspecified</pose>
		<truncated>0</truncated>
		<difficult>0</difficult>
		<occluded>0</occluded>
		<bndbox>
			<xmin>351</xmin>
			<xmax>513</xmax>
			<ymin>1</ymin>
			<ymax>175</ymax>
		</bndbox>
		<polygon>
			<x1>354.722672</x1>
			<y1>0</y1>
			<x2>357.33462</x2>
			<y2>3.458834</y2>
			<x3>361.330452</x3>
			<y3>3.630506</y3>
			<x4>349.663683</x4>
			<y4>23.450369</y4>
			<x5>349.8775</x5>
			<y5>37.00695</y5>
			<x6>357.700925</x6>
			<y6>56.468796</y6>
			<x7>377.32081800000003</x7>
			<y7>79.22661</y7>
			<x8>362.445118</x8>
			<y8>104.088501</y8>
			<x9>362.744761</x9>
			<y9>123.086623</y9>
			<x10>367.27691500000003</x10>
			<y10>134.360976</y10>
			<x11>374.203046</x11>
			<y11>149.618812</y11>
			<x12>394.7574</x12>
			<y12>173.020765</y12>
			<x13>422.799026</x13>
			<y13>174</y13>
			<x14>448.050242</x14>
			<y14>174</y14>
			<x15>512</x15>
			<y15>154.949359</y15>
			<x16>512</x16>
			<y16>95.93348</y16>
			<x17>473.435907</x17>
			<y17>0</y17>
			<x18>354.722672</x18>
			<y18>0</y18>
		</polygon>
	</object>
	<object>
		<name>tanks</name>
		<pose>Unspecified</pose>
		<truncated>0</truncated>
		<difficult>0</difficult>
		<occluded>0</occluded>
		<bndbox>
			<xmin>24</xmin>
			<xmax>201</xmax>
			<ymin>178</ymin>
			<ymax>349</ymax>
		</bndbox>
		<polygon>
			<x1>23.154533</x1>
			<y1>177</y1>
			<x2>35.402724</x2>
			<y2>207.469057</y2>
			<x3>24.484116</x3>
			<y3>236.275977</y3>
			<x4>28.963646</x4>
			<y4>257.323651</y4>
			<x5>64.877679</x5>
			<y5>346.664738</y5>
			<x6>103.114576</x6>
			<y6>348</y6>
			<x7>131.004447</x7>
			<y7>348</y7>
			<x8>199.785446</x8>
			<y8>327.510132</y8>
			<x9>199.785446</x9>
			<y9>288.978165</y9>
			<x10>154.771584</x10>
			<y10>177</y10>
			<x11>23.154533</x11>
			<y11>177</y11>
		</polygon>
	</object>
	<object>
		<name>tanks</name>
		<pose>Unspecified</pose>
		<truncated>0</truncated>
		<difficult>0</difficult>
		<occluded>0</occluded>
		<bndbox>
			<xmin>422</xmin>
			<xmax>477</xmax>
			<ymin>178</ymin>
			<ymax>304</ymax>
		</bndbox>
		<polygon>
			<x1>427.661426</x1>
			<y1>211.09238</y1>
			<x2>434.613644</x2>
			<y2>215.834518</y2>
			<x3>434.885218</x3>
			<y3>221.370895</y3>
			<x4>430.277564</x4>
			<y4>224.470986</y4>
			<x5>428.448986</x5>
			<y5>221.43999300000002</y5>
			<x6>427.561855</x6>
			<y6>226.186012</y6>
			<x7>442.0366</x7>
			<y7>253.00455599999998</y7>
			<x8>446.083016</x8>
			<y8>272.709897</y8>
			<x9>443.780162</x9>
			<y9>302.692308</y9>
			<x10>445.705133</x10>
			<y10>302.692308</y10>
			<x11>475.937676</x11>
			<y11>290.582553</y11>
			<x12>475.937676</x12>
			<y12>263.972854</y12>
			<x13>451.980641</x13>
			<y13>183.84009</y13>
			<x14>449.178889</x14>
			<y14>187.419732</y14>
			<x15>447.169261</x15>
			<y15>180.697821</y15>
			<x16>449.761934</x16>
			<y16>177.181431</y16>
			<x17>429.974027</x17>
			<y17>177.181431</y17>
			<x18>420.98</x18>
			<y18>180.784021</y18>
			<x19>420.98</x19>
			<y19>183.284003</y19>
			<x20>428.792967</x20>
			<y20>205.62122</y20>
			<x21>427.661426</x21>
			<y21>211.09238</y21>
		</polygon>
	</object>
	<object>
		<name>tanks</name>
		<pose>Unspecified</pose>
		<truncated>0</truncated>
		<difficult>0</difficult>
		<occluded>0</occluded>
		<bndbox>
			<xmin>506</xmin>
			<xmax>513</xmax>
			<ymin>260</ymin>
			<ymax>271</ymax>
		</bndbox>
		<polygon>
			<x1>512</x1>
			<y1>258.989536</y1>
			<x2>504.79296899999997</x2>
			<y2>258.568209</y2>
			<x3>506.79492200000004</x3>
			<y3>262.33673899999997</y3>
			<x4>511.59961</x4>
			<y4>259.10657100000003</y4>
			<x5>512</x5>
			<y5>270.412159</y5>
			<x6>512</x6>
			<y6>258.989536</y6>
		</polygon>
	</object>
	<object>
		<name>tanks</name>
		<pose>Unspecified</pose>
		<truncated>0</truncated>
		<difficult>0</difficult>
		<occluded>0</occluded>
		<bndbox>
			<xmin>507</xmin>
			<xmax>513</xmax>
			<ymin>246</ymin>
			<ymax>256</ymax>
		</bndbox>
		<polygon>
			<x1>512</x1>
			<y1>245.080839</y1>
			<x2>506.79492200000004</x2>
			<y2>246.185897</y2>
			<x3>505.99414</x3>
			<y3>254.799679</y3>
			<x4>511.59961</x4>
			<y4>254.799679</y4>
			<x5>512</x5>
			<y5>252.646234</y5>
			<x6>512</x6>
			<y6>245.080839</y6>
		</polygon>
	</object>
</annotation>
